da/__init__.py
da/adv_conf.json
da/base.py
da/cmd.py
da/coral.py
da/da_helpers.py
da/da_spec_conf.json
da/dann.py
da/deep_j_dot.py
da/helpers.py
da/mmd.py
da/swd.py
da/wdgrl.py
da-0.0.2.dist-info/LICENSE
da-0.0.2.dist-info/METADATA
da-0.0.2.dist-info/WHEEL
da-0.0.2.dist-info/top_level.txt
da-0.0.2.dist-info/RECORD
