Metadata-Version: 2.1
Name: da
Version: 0.0.2
Summary: Pytorch domain adaptation package
Home-page: https://github.com/CPJKU/da
Author: Schmid, F. and Masoudian, S.
Author-email: florian.schmid@jku.at, shahed.masoudian@jku.at
License: GPLv2
Keywords: deep learning,pytorch,AI,domain adaptation
Platform: UNKNOWN
Classifier: Environment :: Console
Classifier: Natural Language :: English
Classifier: Development Status :: 3 - Alpha
Classifier: Operating System :: OS Independent
Classifier: Programming Language :: Python :: 3
Classifier: Programming Language :: Python :: 3.7
Requires-Python: >=3.7
License-File: LICENSE
Requires-Dist: numpy (==1.21.5)
Requires-Dist: POT (==0.8.0)
Requires-Dist: scipy (==1.7.3)
Requires-Dist: torch (==1.10.1)
